pybites_search/__init__.py
pybites_search/__main__.py
pybites_search/all_content.py
pybites_search/article.py
pybites_search/base.py
pybites_search/bite.py
pybites_search/cli.py
pybites_search/podcast.py
pybites_search/tip.py
pybites_search/youtube.py
pybites_search-1.1.0.dist-info/WHEEL
pybites_search-1.1.0.dist-info/entry_points.txt
pybites_search-1.1.0.dist-info/METADATA
pybites_search-1.1.0.dist-info/RECORD
