Metadata-Version: 2.3
Name: pybites-search
Version: 1.1.0
Summary: A search engine for Pybites content
Author: Pybites
Author-email: Pybites <info@pybit.es>
Classifier: Programming Language :: Python :: 3
Classifier: License :: OSI Approved :: MIT License
Classifier: Operating System :: OS Independent
Requires-Dist: python-decouple
Requires-Dist: requests
Requires-Dist: requests-cache
Requires-Dist: typer
Requires-Python: >=3.12
Project-URL: Bug Tracker, https://github.com/pybites/search/issues
Project-URL: Homepage, https://github.com/pybites/search
